github_action_template/__init__.py
github_action_template/entrypoint.py
github_action_template/framework.py
github_action_template-0.0.1.dist-info/LICENSE
github_action_template-0.0.1.dist-info/METADATA
github_action_template-0.0.1.dist-info/WHEEL
github_action_template-0.0.1.dist-info/entry_points.txt
github_action_template-0.0.1.dist-info/top_level.txt
github_action_template-0.0.1.dist-info/RECORD
