Metadata-Version: 2.1
Name: github_action_template
Version: 0.0.1
Summary: A light template and boilerplate generator for GitHub actions written in Python 3.8+
Home-page: https://github.com/Talentia-Software/OSS-github-action-python-template
Author: Talentia Software
Author-email: grams@talentia-software.com
License: BSD-3-Clause
Platform: UNKNOWN
Classifier: Development Status :: 4 - Beta
Classifier: Programming Language :: Python :: 3.8
Classifier: License :: OSI Approved :: BSD License
Classifier: Operating System :: OS Independent
Classifier: Topic :: Software Development :: Build Tools
Classifier: Topic :: Software Development :: Version Control :: Git
Requires-Python: >=3.8
